{
	"name": "DCACharges",
	"properties": {
		"linkedServiceName": {
			"referenceName": "AzureBlobStorageLS",
			"type": "LinkedServiceReference"
		},
		"annotations": [],
		"type": "DelimitedText",
		"typeProperties": {
			"location": {
				"type": "AzureBlobStorageLocation",
				"fileName": "Charges.csv",
				"container": "jaw"
			},
			"columnDelimiter": ",",
			"escapeChar": "\\",
			"firstRowAsHeader": true,
			"quoteChar": "\""
		},
		"schema": [
			{
				"name": "Record ID",
				"type": "String"
			},
			{
				"name": "Certificate Number",
				"type": "String"
			},
			{
				"name": "Business Name",
				"type": "String"
			},
			{
				"name": "Violation Date",
				"type": "String"
			},
			{
				"name": "Industry",
				"type": "String"
			},
			{
				"name": "Borough",
				"type": "String"
			},
			{
				"name": "Charge",
				"type": "String"
			},
			{
				"name": "Charge Count",
				"type": "String"
			},
			{
				"name": "Outcome",
				"type": "String"
			},
			{
				"name": "Counts Settled",
				"type": "String"
			},
			{
				"name": "Counts Guilty",
				"type": "String"
			},
			{
				"name": "Counts Not Guilty",
				"type": "String"
			},
			{
				"name": "Building Number",
				"type": "String"
			},
			{
				"name": "Street",
				"type": "String"
			},
			{
				"name": "Street 2",
				"type": "String"
			},
			{
				"name": "Unit Type",
				"type": "String"
			},
			{
				"name": "Unit",
				"type": "String"
			},
			{
				"name": "Description",
				"type": "String"
			},
			{
				"name": "City",
				"type": "String"
			},
			{
				"name": "State",
				"type": "String"
			},
			{
				"name": "Zip",
				"type": "String"
			},
			{
				"name": "Longitude",
				"type": "String"
			},
			{
				"name": "Latitude",
				"type": "String"
			}
		]
	}
}